jblibpandas/__init__.py
jblibpandas/math/__init__.py
jblibpandas/math/math_libs.py
jblibpandas-1.1.1.dist-info/METADATA
jblibpandas-1.1.1.dist-info/WHEEL
jblibpandas-1.1.1.dist-info/top_level.txt
jblibpandas-1.1.1.dist-info/RECORD
