Metadata-Version: 2.1
Name: jblibpandas
Version: 1.1.1
Summary: JustBard's Python Pandas Utilities
Home-page: http://justbard.com
Author: Justin Bard
Author-email: JustinBard@gmail.com
License: UNKNOWN
Platform: UNKNOWN
Classifier: Programming Language :: Python :: 3
Classifier: License :: OSI Approved :: MIT License
Classifier: Operating System :: POSIX :: Linux
Requires-Dist: pandas
Requires-Dist: numpy
